msfi/MSFInteract.py
msfi/__init__.py
msfi/setup.py
msfi-1.1.dist-info/LICENSE
msfi-1.1.dist-info/METADATA
msfi-1.1.dist-info/WHEEL
msfi-1.1.dist-info/top_level.txt
msfi-1.1.dist-info/RECORD
