Metadata-Version: 2.1
Name: msfi
Version: 1.1
Summary: This module allow scripting to control the Metasploit Console
Home-page: http://github.com/Remigascou/msfi
Author: Remi GASCOU
Author-email: remi@gascou.net
License: GPL2
Platform: UNKNOWN
Classifier: Programming Language :: Python :: 3
Classifier: License :: OSI Approved :: GNU General Public License v2 (GPLv2)
Classifier: Topic :: Security
Requires-Python: >=3.6
